cathub/__init__.py
cathub/ase_connect.py
cathub/cathubsql.py
cathub/cathubsqlite.py
cathub/classification.py
cathub/cli.py
cathub/config.py
cathub/create_user.py
cathub/db2server.py
cathub/folder2db.py
cathub/folderreader.py
cathub/make_folders_template.py
cathub/organize.py
cathub/pet_barriers.py
cathub/postgresql.py
cathub/psql_server_connect.py
cathub/query.py
cathub/reaction_networks.py
cathub/test_db.py
cathub/tools.py
cathub/ase_tools/__init__.py
cathub/ase_tools/gas_phase_references.py
Cathub-0.1.7.dist-info/LICENSE
Cathub-0.1.7.dist-info/METADATA
Cathub-0.1.7.dist-info/WHEEL
Cathub-0.1.7.dist-info/entry_points.txt
Cathub-0.1.7.dist-info/top_level.txt
Cathub-0.1.7.dist-info/RECORD
