Metadata-Version: 2.1
Name: Cathub
Version: 0.1.7
Summary: Python API for the Surface Reactions database on Catalysis-Hub.org
Home-page: https://github.com/SUNCAT-Center/CatHub
Author: Kirsten Winther
Author-email: winther@stanford.edu
License: GPL-3.0
Platform: UNKNOWN
Classifier: Development Status :: 4 - Beta
Classifier: Intended Audience :: Developers
Classifier: Topic :: Scientific/Engineering :: Chemistry
Classifier: License :: OSI Approved :: GNU General Public License v3 (GPLv3)
Classifier: Programming Language :: Python
Classifier: Programming Language :: Python :: 3.5
Classifier: Programming Language :: Python :: 3.6
Classifier: Programming Language :: Python :: 3.7
Requires-Python: >=3.5
Requires-Dist: ase (>=3.17)
Requires-Dist: numpy (>=1.16.5)
Requires-Dist: click (>=6.7)
Requires-Dist: future (>=0.16)
Requires-Dist: pathlib2 (>=2.3)
Requires-Dist: psycopg2-binary (>=2)
Requires-Dist: pyyaml (>=3.13)
Requires-Dist: requests (>=2.21)
Requires-Dist: tabulate (>=0.8.2)
Requires-Dist: pandas (>=0.23.4)
Requires-Dist: seaborn (>=0.9.0)
Requires-Dist: sqlalchemy (>=1.3.8)
